LICENSE
README.md
setup.py
karuoflow/__init__.py
karuoflow/datadef.py
karuoflow/error_code.py
karuoflow/flowapp.py
karuoflow/flowmodelagent.py
karuoflow/initflow.py
karuoflow.egg-info/PKG-INFO
karuoflow.egg-info/SOURCES.txt
karuoflow.egg-info/dependency_links.txt
karuoflow.egg-info/requires.txt
karuoflow.egg-info/top_level.txt
karuoflow/db/__init__.py
karuoflow/db/session.py
karuoflow/db/tables.py
karuoflow/test/__init__.py
karuoflow/test/test_initenvironment.py