Metadata-Version: 2.1
Name: karuoflow
Version: 1.35
Summary: flow tempaltes
Home-page: https://github.com/caimmy/karuoflow
Author: caimmy
Author-email: caimmy@hotmail.com
License: MIT Licence
Keywords: Approval flow,work flow
Platform: any
License-File: LICENSE
